multiplier/simulation/lrc_model.vhd
LIBRARY ieee  ; 
LIBRARY std  ; 
    USE ieee.NUMERIC_STD.all  ; 
    USE ieee.std_logic_1164.all  ; 
    USE ieee.std_logic_textio.all  ; 
    use ieee.math_real.all;
    USE std.textio.all  ; 

library math_library;
    use math_library.multiplier_pkg.all;

entity lrc_model is
end;

architecture sim of lrc_model is
    signal rstn : std_logic;

    signal simulation_running : boolean;
    signal simulator_clock : std_logic;
    signal clocked_reset : std_logic;
    constant clock_per : time := 8.4 ns;
    constant clock_half_per : time := 4.2 ns;
    constant simtime_in_clocks : integer := 25e3;

    signal simulation_counter : natural := 0;
    signal multiplier_output : signed(35 downto 0);
    signal multiplier_is_ready_when_1 : std_logic;
    signal int18_multiplier_output : int18 := 0;

    signal hw_multiplier : multiplier_record := multiplier_init_values;
    signal hw_multiplier2 : multiplier_record := multiplier_init_values;
------------------------------------------------------------------------
    signal shift_register : std_logic_vector(2 downto 0);

    signal signal_multiplier_is_ready : boolean := false;

------------------------------------------------------------------------
    type state_variable_record is record
        state                    : int18;
        state_equation           : int18;
        integrator_state_counter : natural range 0 to 7;
    end record;

    constant init_state_variable : state_variable_record := (0,0,0);


    --------------------------------------------------
    procedure create_state_variable
    (
        signal state_variable : inout state_variable_record;
        signal multiplier : inout multiplier_record;
        state_equation : in int18;
        integrator_gain : in int18
    ) is
        alias integrator_state_counter is state_variable.integrator_state_counter;
    begin
        CASE integrator_state_counter is
            WHEN 0 =>
                sequential_multiply(multiplier, integrator_gain, state_equation);
                if multiplier_is_ready(multiplier) then
                    state_variable.state <= state_variable.state + get_multiplier_result(multiplier, 15);
                    integrator_state_counter <= integrator_state_counter + 1;
                end if;
            WHEN others => -- wait for being set to zero
        end CASE;
    end procedure create_state_variable;

    procedure integrate
    (
        signal state_variable : inout state_variable_record;
        signal multiplier : inout multiplier_record 
    ) is
    begin
        
    end integrate;
------------------------------------------------------------------------ 
    -- lrc model signals
    signal inductor_current : int18  := 0;
    signal inductor2_current : int18  := 0;

    signal capacitor_voltage : int18 := 0;
    signal capacitor2_voltage : int18 := 0;
    signal input_voltage : int18     := 0;
    signal capacitor_delta : int18   := 0;

    signal inductor_current_delta : int18 := 0;

    signal inductor_integrator_gain : int18  := 25e3;
    signal capacitor_integrator_gain : int18 := 2000;
    signal load_resistance : int18           := 10;

    signal inductor_series_resistance : int18 := 500;

    signal load_current : int18 := 0;

    signal process_counter : natural := 0;

    signal simulation_trigger_counter : natural := 0;
begin

------------------------------------------------------------------------
    simtime : process
    begin
        simulation_running <= true;
        wait for simtime_in_clocks*clock_per;
        simulation_running <= false;
        wait;
    end process simtime;	

------------------------------------------------------------------------
    sim_clock_gen : process
    begin
        simulator_clock <= '0';
        rstn <= '0';
        simulator_clock <= '0';
        wait for clock_half_per;
        while simulation_running loop
            wait for clock_half_per;
                rstn <= '1';
                simulator_clock <= not simulator_clock;
            end loop;
        wait;
    end process;
------------------------------------------------------------------------

    clocked_reset_generator : process(simulator_clock)
        impure function "*" ( left, right : int18)
        return int18
        is
        begin
            sequential_multiply(hw_multiplier, left, right);
            if multiplier_is_ready(hw_multiplier) then
                process_counter <= process_counter + 1;
            end if;
            return get_multiplier_result(hw_multiplier, 15);
        end "*";

    --------------------------------------------------
        procedure calculate_state
        (
            signal multiplier : inout multiplier_record;
            signal state      : inout int18;
            integrator_gain   : int18;
            state_equation    : int18
            
        ) is
        begin
            sequential_multiply(multiplier, integrator_gain, state_equation); 
            if multiplier_is_ready(multiplier) then
                state <= get_multiplier_result(multiplier, 15) + state;
                process_counter <= process_counter + 1;
            end if;
            
        end calculate_state;
    --------------------------------------------------

    begin
        if rising_edge(simulator_clock) then

            create_multiplier(hw_multiplier); 
            create_multiplier(hw_multiplier2); 
            simulation_counter <= simulation_counter + 1;

            simulation_trigger_counter <= simulation_trigger_counter + 1;
            if simulation_trigger_counter = 20 then
                simulation_trigger_counter <= 0;
                process_counter <= 0;
            end if;

            input_voltage <= 32e2;
            if simulation_counter = 12000  then
                -- load_resistance <= 65e3;
                load_current <= -25e3;
            end if;

            CASE process_counter is 
                WHEN 0 => 
                    inductor_current_delta <= inductor_series_resistance * inductor_current;

                WHEN 1 => 
                    calculate_state(hw_multiplier, inductor_current, inductor_integrator_gain, input_voltage - capacitor_voltage - inductor_current_delta);
                    calculate_state(hw_multiplier2, inductor2_current, inductor_integrator_gain, capacitor_voltage - capacitor2_voltage);

                WHEN 2 => 
                    capacitor_delta <= load_resistance * capacitor2_voltage;

                WHEN 3 =>
                    calculate_state(hw_multiplier, capacitor_voltage, capacitor_integrator_gain, inductor_current - inductor2_current );
                    calculate_state(hw_multiplier2, capacitor2_voltage, capacitor_integrator_gain, inductor2_current - load_current - capacitor_delta);
                WHEN others => -- do nothing

            end CASE; 
        end if; -- rstn
    end process clocked_reset_generator;	

------------------------------------------------------------------------
end sim;

multiplier/simulation/lrc_model.vcd
$date
  Tue Sep 21 22:38:43 2021
$end
$version
  GHDL v0
$end
$timescale
  1 fs
$end
$scope module standard $end
$upscope $end
$scope module std_logic_1164 $end
$upscope $end
$scope module numeric_std $end
$upscope $end
$scope module textio $end
$upscope $end
$scope module std_logic_textio $end
$upscope $end
$scope module math_real $end
$upscope $end
$scope module multiplier_pkg $end
$upscope $end
$scope module lrc_model $end
$var reg 1 ! rstn $end
$var reg 1 " simulation_running $end
$var reg 1 # simulator_clock $end
$var reg 1 $ clocked_reset $end
$var integer 32 % simulation_counter $end
$var reg 36 & multiplier_output[35:0] $end
$var reg 1 ' multiplier_is_ready_when_1 $end
$var integer 32 ( int18_multiplier_output $end
$comment hw_multiplier is not handled $end
$comment hw_multiplier2 is not handled $end
$var reg 3 ) shift_register[2:0] $end
$var reg 1 * signal_multiplier_is_ready $end
$var integer 32 + inductor_current $end
$var integer 32 , inductor2_current $end
$var integer 32 - capacitor_voltage $end
$var integer 32 . capacitor2_voltage $end
$var integer 32 / input_voltage $end
$var integer 32 0 capacitor_delta $end
$var integer 32 1 inductor_current_delta $end
$var integer 32 2 inductor_integrator_gain $end
$var integer 32 3 capacitor_integrator_gain $end
$var integer 32 4 load_resistance $end
$var integer 32 5 inductor_series_resistance $end
$var integer 32 6 load_current $end
$var integer 32 7 process_counter $end
$var integer 32 8 simulation_trigger_counter $end
$upscope $end
$enddefinitions $end
#0
0!
1"
0#
U$
b0 %
bUUUUUUUUUUUUUUUUUUUUUUUUUUUUUUUUUUUU &
U'
b0 (
bUUU )
0*
b0 +
b0 ,
b0 -
b0 .
b0 /
b0 0
b0 1
b110000110101000 2
b11111010000 3
b1010 4
b111110100 5
b0 6
b0 7
b0 8
#4200000
#8400000
1!
1#
b1 %
b110010000000 /
b1 8
#12600000
0#
#16800000
1#
b10 %
b10 8
#21000000
0#
#25200000
1#
b11 %
b11 8
#29400000
0#
#33600000
1#
b100 %
b100 8
#37800000
0#
#42000000
1#
b101 %
b1 7
b101 8
#46200000
0#
#50400000
1#
b110 %
b110 8
#54600000
0#
#58800000
1#
b111 %
b111 8
#63000000
0#
#67200000
1#
b1000 %
b1000 8
#71400000
0#
#75600000
1#
b1001 %
b1001 8
#79800000
0#
#84000000
1#
b1010 %
b100110001001 +
b10 7
b1010 8
#88200000
0#
#92400000
1#
b1011 %
b100110001001 0
b1011 8
#96600000
0#
#100800000
1#
b1100 %
b1100 8
#105000000
0#
#109200000
1#
b1101 %
b1101 8
#113400000
0#
#117600000
1#
b1110 %
b1110 8
#121800000
0#
#126000000
1#
b1111 %
b0 0
b11 7
b1111 8
#130200000
0#
#134400000
1#
b10000 %
b10000 8
#138600000
0#
#142800000
1#
b10001 %
b10001 8
#147000000
0#
#151200000
1#
b10010 %
b10010 8
#155400000
0#
#159600000
1#
b10011 %
b10011 8
#163800000
0#
#168000000
1#
b10100 %
b10010101 -
b100 7
b10100 8
#172200000
0#
#176400000
1#
b10101 %
b0 7
b0 8
#180600000
0#
#184800000
1#
b10110 %
b10010101 1
b1 8
#189000000
0#
#193200000
1#
b10111 %
b10 8
#197400000
0#
#201600000
1#
b11000 %
b11 8
#205800000
0#
#210000000
1#
b11001 %
b100 8
#214200000
0#
#218400000
1#
b11010 %
b100101 1
b1 7
b101 8
#222600000
0#
#226800000
1#
b11011 %
b110 8
#231000000
0#
#235200000
1#
b11100 %
b111 8
#239400000
0#
#243600000
1#
b11101 %
b1000 8
#247800000
0#
#252000000
1#
b11110 %
b1001 8
#256200000
0#
#260400000
1#
b11111 %
b1001010000100 +
b1110010 ,
b10 7
b1010 8
#264600000
0#
#268800000
1#
b100000 %
b100011111011 0
b1011 8
#273000000
0#
#277200000
1#
b100001 %
b1100 8
#281400000
0#
#285600000
1#
b100010 %
b1101 8
#289800000
0#
#294000000
1#
b100011 %
b1110 8
#298200000
0#
#302400000
1#
b100100 %
b0 0
b11 7
b1111 8
#306600000
0#
#310800000
1#
b100101 %
b10000 8
#315000000
0#
#319200000
1#
b100110 %
b10001 8
#323400000
0#
#327600000
1#
b100111 %
b10010 8
#331800000
0#
#336000000
1#
b101000 %
b10011 8
#340200000
0#
#344400000
1#
b101001 %
b110101111 -
b111 .
b100 7
b10100 8
#348600000
0#
#352800000
1#
b101010 %
b0 7
b0 8
#357000000
0#
#361200000
1#
b101011 %
b100011010 1
b1 8
#365400000
0#
#369600000
1#
b101100 %
b10 8
#373800000
0#
#378000000
1#
b101101 %
b11 8
#382200000
0#
#386400000
1#
b101110 %
b100 8
#390600000
0#
#394800000
1#
b101111 %
b1001000 1
b1 7
b101 8
#399000000
0#
#403200000
1#
b110000 %
b110 8
#407400000
0#
#411600000
1#
b110001 %
b111 8
#415800000
0#
#420000000
1#
b110010 %
b1000 8
#424200000
0#
#428400000
1#
b110011 %
b1001 8
#432600000
0#
#436800000
1#
b110100 %
b1101010001110 +
b110110101 ,
b10 7
b1010 8
#441000000
0#
#445200000
1#
b110101 %
b100000001010 0
b1011 8
#449400000
0#
#453600000
1#
b110110 %
b1100 8
#457800000
0#
#462000000
1#
b110111 %
b1101 8
#466200000
0#
#470400000
1#
b111000 %
b1110 8
#474600000
0#
#478800000
1#
b111001 %
b0 0
b11 7
b1111 8
#483000000
0#
#487200000
1#
b111010 %
b10000 8
#491400000
0#
#495600000
1#
b111011 %
b10001 8
#499800000
0#
#504000000
1#
b111100 %
b10010 8
#508200000
0#
#512400000
1#
b111101 %
b10011 8
#516600000
0#
#520800000
1#
b111110 %
b1100110011 -
b100010 .
b100 7
b10100 8
#525000000
0#
#529200000
1#
b111111 %
b0 7
b0 8
#533400000
0#
#537600000
1#
b1000000 %
b110000100 1
b1 8
#541800000
0#
#546000000
1#
b1000001 %
b10 8
#550200000
0#
#554400000
1#
b1000010 %
b11 8
#558600000
0#
#562800000
1#
b1000011 %
b100 8
#567000000
0#
#571200000
1#
b1000100 %
b1101000 1
b1 7
b101 8
#575400000
0#
#579600000
1#
b1000101 %
b110 8
#583800000
0#
#588000000
1#
b1000110 %
b111 8
#592200000
0#
#596400000
1#
b1000111 %
b1000 8
#600600000
0#
#604800000
1#
b1001000 %
b1001 8
#609000000
0#
#613200000
1#
b1001001 %
b10000101010111 +
b10000001100 ,
b10 7
b1010 8
#617400000
0#
#621600000
1#
b1001010 %
b11011001001 0
b1011 8
#625800000
0#
#630000000
1#
b1001011 %
b1100 8
#634200000
0#
#638400000
1#
b1001100 %
b1101 8
#642600000
0#
#646800000
1#
b1001101 %
b1110 8
#651000000
0#
#655200000
1#
b1001110 %
b0 0
b11 7
b1111 8
#659400000
0#
#663600000
1#
b1001111 %
b10000 8
#667800000
0#
#672000000
1#
b1010000 %
b10001 8
#676200000
0#
#680400000
1#
b1010001 %
b10010 8
#684600000
0#
#688800000
1#
b1010010 %
b10011 8
#693000000
0#
#697200000
1#
b1010011 %
b10011111101 -
b1100001 .
b100 7
b10100 8
#701400000
0#
#705600000
1#
b1010100 %
b0 7
b0 8
#709800000
0#
#714000000
1#
b1010101 %
b111001010 1
b1 8
#718200000
0#
#722400000
1#
b1010110 %
b10 8
#726600000
0#
#730800000
1#
b1010111 %
b11 8
#735000000
0#
#739200000
1#
b1011000 %
b100 8
#743400000
0#
#747600000
1#
b1011001 %
b10000010 1
b1 7
b101 8
#751800000
0#
#756000000
1#
b1011010 %
b110 8
#760200000
0#
#764400000
1#
b1011011 %
b111 8
#768600000
0#
#772800000
1#
b1011100 %
b1000 8
#777000000
0#
#781200000
1#
b1011101 %
b1001 8
#785400000
0#
#789600000
1#
b1011110 %
b10011010101111 +
b11110010000 ,
b10 7
b1010 8
#793800000
0#
#798000000
1#
b1011111 %
b10101011000 0
b1011 8
#802200000
0#
#806400000
1#
b1100000 %
b1100 8
#810600000
0#
#814800000
1#
b1100001 %
b1101 8
#819000000
0#
#823200000
1#
b1100010 %
b1110 8
#827400000
0#
#831600000
1#
b1100011 %
b0 0
b11 7
b1111 8
#835800000
0#
#840000000
1#
b1100100 %
b10000 8
#844200000
0#
#848400000
1#
b1100101 %
b10001 8
#852600000
0#
#856800000
1#
b1100110 %
b10010 8
#861000000
0#
#865200000
1#
b1100111 %
b10011 8
#869400000
0#
#873600000
1#
b1101000 %
b11011100011 -
b11010111 .
b100 7
b10100 8
#877800000
0#
#882000000
1#
b1101001 %
b0 7
b0 8
#886200000
0#
#890400000
1#
b1101010 %
b111100110 1
b1 8
#894600000
0#
#898800000
1#
b1101011 %
b10 8
#903000000
0#
#907200000
1#
b1101100 %
b11 8
#911400000
0#
#915600000
1#
b1101101 %
b100 8
#919800000
0#
#924000000
1#
b1101110 %
b10010111 1
b1 7
b101 8
#928200000
0#
#932400000
1#
b1101111 %
b110 8
#936600000
0#
#940800000
1#
b1110000 %
b111 8
#945000000
0#
#949200000
1#
b1110001 %
b1000 8
#953400000
0#
#957600000
1#
b1110010 %
b1001 8
#961800000
0#
#966000000
1#
b1110011 %
b10101010000100 +
b110000101101 ,
b10 7
b1010 8
#970200000
0#
#974400000
1#
b1110100 %
b1111010101 0
b1011 8
#978600000
0#
#982800000
1#
b1110101 %
b1100 8
#987000000
0#
#991200000
1#
b1110110 %
b1101 8
#995400000
0#
#999600000
1#
b1110111 %
b1110 8
#1003800000
0#
#1008000000
1#
b1111000 %
b0 0
b11 7
b1111 8
#1012200000
0#
#1016400000
1#
b1111001 %
b10000 8
#1020600000
0#
#1024800000
1#
b1111010 %
b10001 8
#1029000000
0#
#1033200000
1#
b1111011 %
b10010 8
#1037400000
0#
#1041600000
1#
b1111100 %
b10011 8
#1045800000
0#
#1050000000
1#
b1111101 %
b100010111101 -
b110010101 .
b100 7
b10100 8
#1054200000
0#
#1058400000
1#
b1111110 %
b0 7
b0 8
#1062600000
0#
#1066800000
1#
b1111111 %
b111011010 1
b1 8
#1071000000
0#
#1075200000
1#
b10000000 %
b10 8
#1079400000
0#
#1083600000
1#
b10000001 %
b11 8
#1087800000
0#
#1092000000
1#
b10000010 %
b100 8
#1096200000
0#
#1100400000
1#
b10000011 %
b10100110 1
b1 7
b101 8
#1104600000
0#
#1108800000
1#
b10000100 %
b110 8
#1113000000
0#
#1117200000
1#
b10000101 %
b111 8
#1121400000
0#
#1125600000
1#
b10000110 %
b1000 8
#1129800000
0#
#1134000000
1#
b10000111 %
b1001 8
#1138200000
0#
#1142400000
1#
b10001000 %
b10110011100100 +
b1000110100011 ,
b10 7
b1010 8
#1146600000
0#
#1150800000
1#
b10001001 %
b1001100000 0
b1011 8
#1155000000
0#
#1159200000
1#
b10001010 %
b1100 8
#1163400000
0#
#1167600000
1#
b10001011 %
b1101 8
#1171800000
0#
#1176000000
1#
b10001100 %
b1110 8
#1180200000
0#
#1184400000
1#
b10001101 %
b0 0
b11 7
b1111 8
#1188600000
0#
#1192800000
1#
b10001110 %
b10000 8
#1197000000
0#
#1201200000
1#
b10001111 %
b10001 8
#1205400000
0#
#1209600000
1#
b10010000 %
b10010 8
#1213800000
0#
#1218000000
1#
b10010001 %
b10011 8
#1222200000
0#
#1226400000
1#
b10010010 %
b101001100111 -
b1010101001 .
b100 7
b10100 8
#1230600000
0#
#1234800000
1#
b10010011 %
b0 7
b0 8
#1239000000
0#
#1243200000
1#
b10010100 %
b110101010 1
b1 8
#1247400000
0#
#1251600000
1#
b10010101 %
b10 8
#1255800000
0#
#1260000000
1#
b10010110 %
b11 8
#1264200000
0#
#1268400000
1#
b10010111 %
b100 8
#1272600000
0#
#1276800000
1#
b10011000 %
b10101111 1
b1 7
b101 8
#1281000000
0#
#1285200000
1#
b10011001 %
b110 8
#1289400000
0#
#1293600000
1#
b10011010 %
b111 8
#1297800000
0#
#1302000000
1#
b10011011 %
b1000 8
#1306200000
0#
#1310400000
1#
b10011100 %
b1001 8
#1314600000
0#
#1318800000
1#
b10011101 %
b10110111111000 +
b1011110001011 ,
b10 7
b1010 8
#1323000000
0#
#1327200000
1#
b10011110 %
b100010100 0
b1011 8
#1331400000
0#
#1335600000
1#
b10011111 %
b1100 8
#1339800000
0#
#1344000000
1#
b10100000 %
b1101 8
#1348200000
0#
#1352400000
1#
b10100001 %
b1110 8
#1356600000
0#
#1360800000
1#
b10100010 %
b0 0
b11 7
b1111 8
#1365000000
0#
#1369200000
1#
b10100011 %
b10000 8
#1373400000
0#
#1377600000
1#
b10100100 %
b10001 8
#1381800000
0#
#1386000000
1#
b10100101 %
b10010 8
#1390200000
0#
#1394400000
1#
b10100110 %
b10011 8
#1398600000
0#
#1402800000
1#
b10100111 %
b101111000101 -
b10000011001 .
b100 7
b10100 8
#1407000000
0#
#1411200000
1#
b10101000 %
b0 7
b0 8
#1415400000
0#
#1419600000
1#
b10101001 %
b101011110 1
b1 8
#1423800000
0#
#1428000000
1#
b10101010 %
b10 8
#1432200000
0#
#1436400000
1#
b10101011 %
b11 8
#1440600000
0#
#1444800000
1#
b10101100 %
b100 8
#1449000000
0#
#1453200000
1#
b10101101 %
b10110100 1
b1 7
b101 8
#1457400000
0#
#1461600000
1#
b10101110 %
b110 8
#1465800000
0#
#1470000000
1#
b10101111 %
b111 8
#1474200000
0#
#1478400000
1#
b10110000 %
b1000 8
#1482600000
0#
#1486800000
1#
b10110001 %
b1001 8
#1491000000
0#
#1495200000
1#
b10110010 %
b10110111111101 +
b1110101100101 ,
b10 7
b1010 8
#1499400000
0#
#1503600000
1#
b10110011 %
b101 0
b1011 8
#1507800000
0#
#1512000000
1#
b10110100 %
b1100 8
#1516200000
0#
#1520400000
1#
b10110101 %
b1101 8
#1524600000
0#
#1528800000
1#
b10110110 %
b1110 8
#1533000000
0#
#1537200000
1#
b10110111 %
b0 0
b11 7
b1111 8
#1541400000
0#
#1545600000
1#
b10111000 %
b10000 8
#1549800000
0#
#1554000000
1#
b10111001 %
b10001 8
#1558200000
0#
#1562400000
1#
b10111010 %
b10010 8
#1566600000
0#
#1570800000
1#
b10111011 %
b10011 8
#1575000000
0#
#1579200000
1#
b10111100 %
b110011001000 -
b10111100100 .
b100 7
b10100 8
#1583400000
0#
#1587600000
1#
b10111101 %
b0 7
b0 8
#1591800000
0#
#1596000000
1#
b10111110 %
b100000011 1
b1 8
#1600200000
0#
#1604400000
1#
b10111111 %
b10 8
#1608600000
0#
#1612800000
1#
b11000000 %
b11 8
#1617000000
0#
#1621200000
1#
b11000001 %
b100 8
#1625400000
0#
#1629600000
1#
b11000010 %
b10110100 1
b1 7
b101 8
#1633800000
0#
#1638000000
1#
b11000011 %
b110 8
#1642200000
0#
#1646400000
1#
b11000100 %
b111 8
#1650600000
0#
#1654800000
1#
b11000101 %
b1000 8
#1659000000
0#
#1663200000
1#
b11000110 %
b1001 8
#1667400000
0#
#1671600000
1#
b11000111 %
b10110100111100 +
b10001010100111 ,
b10 7
b1010 8
#1675800000
0#
#1680000000
1#
b11001000 %
b11111111111111111111111100111111 0
b1011 8
#1684200000
0#
#1688400000
1#
b11001001 %
b1100 8
#1692600000
0#
#1696800000
1#
b11001010 %
b1101 8
#1701000000
0#
#1705200000
1#
b11001011 %
b1110 8
#1709400000
0#
#1713600000
1#
b11001100 %
b0 0
b11 7
b1111 8
#1717800000
0#
#1722000000
1#
b11001101 %
b10000 8
#1726200000
0#
#1730400000
1#
b11001110 %
b10001 8
#1734600000
0#
#1738800000
1#
b11001111 %
b10010 8
#1743000000
0#
#1747200000
1#
b11010000 %
b10011 8
#1751400000
0#
#1755600000
1#
b11010001 %
b110101101101 -
b100000000001 .
b100 7
b10100 8
#1759800000
0#
#1764000000
1#
b11010010 %
b0 7
b0 8
#1768200000
0#
#1772400000
1#
b11010011 %
b10100101 1
b1 8
#1776600000
0#
#1780800000
1#
b11010100 %
b10 8
#1785000000
0#
#1789200000
1#
b11010101 %
b11 8
#1793400000
0#
#1797600000
1#
b11010110 %
b100 8
#1801800000
0#
#1806000000
1#
b11010111 %
b10110001 1
b1 7
b101 8
#1810200000
0#
#1814400000
1#
b11011000 %
b110 8
#1818600000
0#
#1822800000
1#
b11011001 %
b111 8
#1827000000
0#
#1831200000
1#
b11011010 %
b1000 8
#1835400000
0#
#1839600000
1#
b11011011 %
b1001 8
#1843800000
0#
#1848000000
1#
b11011100 %
b10110000000000 +
b10011011001010 ,
b10 7
b1010 8
#1852200000
0#
#1856400000
1#
b11011101 %
b11111111111111111111111011000100 0
b1011 8
#1860600000
0#
#1864800000
1#
b11011110 %
b1100 8
#1869000000
0#
#1873200000
1#
b11011111 %
b1101 8
#1877400000
0#
#1881600000
1#
b11100000 %
b1110 8
#1885800000
0#
#1890000000
1#
b11100001 %
b0 0
b11 7
b1111 8
#1894200000
0#
#1898400000
1#
b11100010 %
b10000 8
#1902600000
0#
#1906800000
1#
b11100011 %
b10001 8
#1911000000
0#
#1915200000
1#
b11100100 %
b10010 8
#1919400000
0#
#1923600000
1#
b11100101 %
b10011 8
#1927800000
0#
#1932000000
1#
b11100110 %
b110110111110 -
b101001011111 .
b100 7
b10100 8
#1936200000
0#
#1940400000
1#
b11100111 %
b0 7
b0 8
#1944600000
0#
#1948800000
1#
b11101000 %
b1010001 1
b1 8
#1953000000
0#
#1957200000
1#
b11101001 %
b10 8
#1961400000
0#
#1965600000
1#
b11101010 %
b11 8
#1969800000
0#
#1974000000
1#
b11101011 %
b100 8
#1978200000
0#
#1982400000
1#
b11101100 %
b10101100 1
b1 7
b101 8
#1986600000
0#
#1990800000
1#
b11101101 %
b110 8
#1995000000
0#
#1999200000
1#
b11101110 %
b111 8
#2003400000
0#
#2007600000
1#
b11101111 %
b1000 8
#2011800000
0#
#2016000000
1#
b11110000 %
b1001 8
#2020200000
0#
#2024400000
1#
b11110001 %
b10101010001010 +
b10100101011100 ,
b10 7
b1010 8
#2028600000
0#
#2032800000
1#
b11110010 %
b11111111111111111111111010001010 0
b1011 8
#2037000000
0#
#2041200000
1#
b11110011 %
b1100 8
#2045400000
0#
#2049600000
1#
b11110100 %
b1101 8
#2053800000
0#
#2058000000
1#
b11110101 %
b1110 8
#2062200000
0#
#2066400000
1#
b11110110 %
b0 0
b11 7
b1111 8
#2070600000
0#
#2074800000
1#
b11110111 %
b10000 8
#2079000000
0#
#2083200000
1#
b11111000 %
b10001 8
#2087400000
0#
#2091600000
1#
b11111001 %
b10010 8
#2095800000
0#
#2100000000
1#
b11111010 %
b10011 8
#2104200000
0#
#2108400000
1#
b11111011 %
b110111010000 -
b110011100101 .
b100 7
b10100 8
#2112600000
0#
#2116800000
1#
b11111100 %
b0 7
b0 8
#2121000000
0#
#2125200000
1#
b11111101 %
b10010 1
b1 8
#2129400000
0#
#2133600000
1#
b11111110 %
b10 8
#2137800000
0#
#2142000000
1#
b11111111 %
b11 8
#2146200000
0#
#2150400000
1#
b100000000 %
b100 8
#2154600000
0#
#2158800000
1#
b100000001 %
b10100110 1
b1 7
b101 8
#2163000000
0#
#2167200000
1#
b100000010 %
b110 8
#2171400000
0#
#2175600000
1#
b100000011 %
b111 8
#2179800000
0#
#2184000000
1#
b100000100 %
b1000 8
#2188200000
0#
#2192400000
1#
b100000101 %
b1001 8
#2196600000
0#
#2200800000
1#
b100000110 %
b10100100001011 +
b10101000001111 ,
b10 7
b1010 8
#2205000000
0#
#2209200000
1#
b100000111 %
b11111111111111111111111010000001 0
b1011 8
#2213400000
0#
#2217600000
1#
b100001000 %
b1100 8
#2221800000
0#
#2226000000
1#
b100001001 %
b1101 8
#2230200000
0#
#2234400000
1#
b100001010 %
b1110 8
#2238600000
0#
#2242800000
1#
b100001011 %
b1 0
b11 7
b1111 8
#2247000000
0#
#2251200000
1#
b100001100 %
b10000 8
#2255400000
0#
#2259600000
1#
b100001101 %
b10001 8
#2263800000
0#
#2268000000
1#
b100001110 %
b10010 8
#2272200000
0#
#2276400000
1#
b100001111 %
b10011 8
#2280600000
0#
#2284800000
1#
b100010000 %
b110111000000 -
b111101110110 .
b100 7
b10100 8
#2289000000
0#
#2293200000
1#
b100010001 %
b0 7
b0 8
#2297400000
0#
#2301600000
1#
b100010010 %
b11111111111111111111111111110000 1
b1 8
#2305800000
0#
#2310000000
1#
b100010011 %
b10 8
#2314200000
0#
#2318400000
1#
b100010100 %
b11 8
#2322600000
0#
#2326800000
1#
b100010101 %
b100 8
#2331000000
0#
#2335200000
1#
b100010110 %
b10100000 1
b1 7
b101 8
#2339400000
0#
#2343600000
1#
b100010111 %
b110 8
#2347800000
0#
#2352000000
1#
b100011000 %
b111 8
#2356200000
0#
#2360400000
1#
b100011001 %
b1000 8
#2364600000
0#
#2368800000
1#
b100011010 %
b1001 8
#2373000000
0#
#2377200000
1#
b100011011 %
b10011110011100 +
b10100011000000 ,
b10 7
b1010 8
#2381400000
0#
#2385600000
1#
b100011100 %
b11111111111111111111111010010001 0
b1011 8
#2389800000
0#
#2394000000
1#
b100011101 %
b1100 8
#2398200000
0#
#2402400000
1#
b100011110 %
b1101 8
#2406600000
0#
#2410800000
1#
b100011111 %
b1110 8
#2415000000
0#
#2419200000
1#
b100100000 %
b1 0
b11 7
b1111 8
#2423400000
0#
#2427600000
1#
b100100001 %
b10000 8
#2431800000
0#
#2436000000
1#
b100100010 %
b10001 8
#2440200000
0#
#2444400000
1#
b100100011 %
b10010 8
#2448600000
0#
#2452800000
1#
b100100100 %
b10011 8
#2457000000
0#
#2461200000
1#
b100100101 %
b110110101110 -
b1000111110011 .
b100 7
b10100 8
#2465400000
0#
#2469600000
1#
b100100110 %
b0 7
b0 8
#2473800000
0#
#2478000000
1#
b100100111 %
b11111111111111111111111111101110 1
b1 8
#2482200000
0#
#2486400000
1#
b100101000 %
b10 8
#2490600000
0#
#2494800000
1#
b100101001 %
b11 8
#2499000000
0#
#2503200000
1#
b100101010 %
b100 8
#2507400000
0#
#2511600000
1#
b100101011 %
b10011011 1
b1 7
b101 8
#2515800000
0#
#2520000000
1#
b100101100 %
b110 8
#2524200000
0#
#2528400000
1#
b100101101 %
b111 8
#2532600000
0#
#2536800000
1#
b100101110 %
b1000 8
#2541000000
0#
#2545200000
1#
b100101111 %
b1001 8
#2549400000
0#
#2553600000
1#
b100110000 %
b10011000111111 +
b10010101111110 ,
b10 7
b1010 8
#2557800000
0#
#2562000000
1#
b100110001 %
b11111111111111111111111010100011 0
b1011 8
#2566200000
0#
#2570400000
1#
b100110010 %
b1100 8
#2574600000
0#
#2578800000
1#
b100110011 %
b1101 8
#2583000000
0#
#2587200000
1#
b100110100 %
b1110 8
#2591400000
0#
#2595600000
1#
b100110101 %
b1 0
b11 7
b1111 8
#2599800000
0#
#2604000000
1#
b100110110 %
b10000 8
#2608200000
0#
#2612400000
1#
b100110111 %
b10001 8
#2616600000
0#
#2620800000
1#
b100111000 %
b10010 8
#2625000000
0#
#2629200000
1#
b100111001 %
b10011 8
#2633400000
0#
#2637600000
1#
b100111010 %
b110110111010 -
b1010000111101 .
b100 7
b10100 8
#2641800000
0#
#2646000000
1#
b100111011 %
b0 7
b0 8
#2650200000
0#
#2654400000
1#
b100111100 %
b1100 1
b1 8
#2658600000
0#
#2662800000
1#
b100111101 %
b10 8
#2667000000
0#
#2671200000
1#
b100111110 %
b11 8
#2675400000
0#
#2679600000
1#
b100111111 %
b100 8
#2683800000
0#
#2688000000
1#
b101000000 %
b10010101 1
b1 7
b101 8
#2692200000
0#
#2696400000
1#
b101000001 %
b110 8
#2700600000
0#
#2704800000
1#
b101000010 %
b111 8
#2709000000
0#
#2713200000
1#
b101000011 %
b1000 8
#2717400000
0#
#2721600000
1#
b101000100 %
b1001 8
#2725800000
0#
#2730000000
1#
b101000101 %
b10010011011101 +
b10000010000110 ,
b10 7
b1010 8
#2734200000
0#
#2738400000
1#
b101000110 %
b11111111111111111111111010011110 0
b1011 8
#2742600000
0#
#2746800000
1#
b101000111 %
b1100 8
#2751000000
0#
#2755200000
1#
b101001000 %
b1101 8
#2759400000
0#
#2763600000
1#
b101001001 %
b1110 8
#2767800000
0#
#2772000000
1#
b101001010 %
b10 0
b11 7
b1111 8
#2776200000
0#
#2780400000
1#
b101001011 %
b10000 8
#2784600000
0#
#2788800000
1#
b101001100 %
b10001 8
#2793000000
0#
#2797200000
1#
b101001101 %
b10010 8
#2801400000
0#
#2805600000
1#
b101001110 %
b10011 8
#2809800000
0#
#2814000000
1#
b101001111 %
b110111111110 -
b1011000111001 .
b100 7
b10100 8
#2818200000
0#
#2822400000
1#
b101010000 %
b0 7
b0 8
#2826600000
0#
#2830800000
1#
b101010001 %
b1000100 1
b1 8
#2835000000
0#
#2839200000
1#
b101010010 %
b10 8
#2843400000
0#
#2847600000
1#
b101010011 %
b11 8
#2851800000
0#
#2856000000
1#
b101010100 %
b100 8
#2860200000
0#
#2864400000
1#
b101010101 %
b10010000 1
b1 7
b101 8
#2868600000
0#
#2872800000
1#
b101010110 %
b110 8
#2877000000
0#
#2881200000
1#
b101010111 %
b111 8
#2885400000
0#
#2889600000
1#
b101011000 %
b1000 8
