multiplier/simulation/tb_multiplier.vhd
LIBRARY ieee  ; 
LIBRARY std  ; 
    USE ieee.NUMERIC_STD.all  ; 
    USE ieee.std_logic_1164.all  ; 
    USE ieee.std_logic_textio.all  ; 
    use ieee.math_real.all;
    USE std.textio.all  ; 

library math_library;
    use math_library.multiplier_pkg.all;

entity tb_multiplier is
end;

architecture sim of tb_multiplier is
    signal rstn : std_logic;

    signal simulation_running : boolean;
    signal simulator_clock : std_logic;
    signal clocked_reset : std_logic;
    constant clock_per : time := 1 ns;
    constant clock_half_per : time := 0.5 ns;
    constant simtime_in_clocks : integer := 50;

    signal simulation_counter : natural := 0;
    signal multiplier_output : signed(35 downto 0);
    signal multiplier_is_ready_when_1 : std_logic;
    signal int18_multiplier_output : int18 := 0;

    signal hw_multiplier : multiplier_record := multiplier_init_values;

begin

------------------------------------------------------------------------
    simtime : process
    begin
        simulation_running <= true;
        wait for simtime_in_clocks*clock_per;
        simulation_running <= false;
        wait;
    end process simtime;	

------------------------------------------------------------------------
    sim_clock_gen : process
    begin
        simulator_clock <= '0';
        rstn <= '0';
        simulator_clock <= '0';
        wait for clock_half_per;
        while simulation_running loop
            wait for clock_half_per;
                rstn <= '1';
                simulator_clock <= not simulator_clock;
            end loop;
        wait;
    end process;
------------------------------------------------------------------------

    clocked_reset_generator : process(simulator_clock, rstn)

    begin
        if rstn = '0' then
        -- reset state
            clocked_reset <= '0';
    
        elsif rising_edge(simulator_clock) then
            clocked_reset <= '1';

            create_multiplier(hw_multiplier);

            simulation_counter <= simulation_counter + 1;
            CASE simulation_counter is
                WHEN 1 => multiply(hw_multiplier, -3, 1);
                WHEN 2 => multiply(hw_multiplier, -5, 1);
                WHEN 3 => multiply(hw_multiplier, -25, 1);
                WHEN 4 => multiply(hw_multiplier, 100, 1);
                WHEN 5 => multiply(hw_multiplier, 1000, 1);
                WHEN 6 => multiply(hw_multiplier, 985, 1);
                WHEN 7 => multiply(hw_multiplier, 10090, 1);
                WHEN 8 => multiply(hw_multiplier, 33586, 1);
                WHEN 9 =>
                    simulation_counter <= 9;
                    sequential_multiply(hw_multiplier, -1, -1);
                    if multiplier_is_not_busy(hw_multiplier) then
                        simulation_counter <= 10;
                    end if;

                WHEN others => -- do nothing
            end CASE;
            if multiplier_is_ready(hw_multiplier) then
                int18_multiplier_output <= get_multiplier_result(hw_multiplier,1);
                report "multiplication result at simulation_counter value " & 
                    integer'image(simulation_counter)  &" : " & integer'image((get_multiplier_result(hw_multiplier,0)));
            end if; 

        end if; -- rstn
    end process clocked_reset_generator;	
------------------------------------------------------------------------
end sim;

multiplier/simulation/tb_multiplier.vcd
$date
  Sun Sep 26 14:02:05 2021
$end
$version
  GHDL v0
$end
$timescale
  1 fs
$end
$scope module standard $end
$upscope $end
$scope module std_logic_1164 $end
$upscope $end
$scope module numeric_std $end
$upscope $end
$scope module textio $end
$upscope $end
$scope module std_logic_textio $end
$upscope $end
$scope module math_real $end
$upscope $end
$scope module multiplier_pkg $end
$upscope $end
$scope module tb_multiplier $end
$var reg 1 ! rstn $end
$var reg 1 " simulation_running $end
$var reg 1 # simulator_clock $end
$var reg 1 $ clocked_reset $end
$var integer 32 % simulation_counter $end
$var reg 36 & multiplier_output[35:0] $end
$var reg 1 ' multiplier_is_ready_when_1 $end
$var integer 32 ( int18_multiplier_output $end
$comment hw_multiplier is not handled $end
$upscope $end
$enddefinitions $end
#0
0!
1"
0#
0$
b0 %
bUUUUUUUUUUUUUUUUUUUUUUUUUUUUUUUUUUUU &
U'
b0 (
#500000
#1000000
1!
1#
1$
b1 %
#1500000
0#
#2000000
1#
b10 %
#2500000
0#
#3000000
1#
b11 %
#3500000
0#
#4000000
1#
b100 %
#4500000
0#
#5000000
1#
b101 %
#5500000
0#
#6000000
1#
b110 %
b11111111111111111111111111111110 (
#6500000
0#
#7000000
1#
b111 %
b11111111111111111111111111111101 (
#7500000
0#
#8000000
1#
b1000 %
b11111111111111111111111111110011 (
#8500000
0#
#9000000
1#
b1001 %
b110010 (
#9500000
0#
#10000000
1#
b111110100 (
#10500000
0#
#11000000
1#
b111101101 (
#11500000
0#
#12000000
1#
b1001110110101 (
#12500000
0#
#13000000
1#
b100000110011001 (
#13500000
0#
#14000000
1#
b1010 %
#14500000
0#
#15000000
1#
b1011 %
#15500000
0#
#16000000
1#
b1100 %
#16500000
0#
#17000000
1#
b1101 %
#17500000
0#
#18000000
1#
b1110 %
b0 (
#18500000
0#
#19000000
1#
b1111 %
#19500000
0#
#20000000
1#
b10000 %
#20500000
0#
#21000000
1#
b10001 %
#21500000
0#
#22000000
1#
b10010 %
#22500000
0#
#23000000
1#
b10011 %
#23500000
0#
#24000000
1#
b10100 %
#24500000
0#
#25000000
1#
b10101 %
#25500000
0#
#26000000
1#
b10110 %
#26500000
0#
#27000000
1#
b10111 %
#27500000
0#
#28000000
1#
b11000 %
#28500000
0#
#29000000
1#
b11001 %
#29500000
0#
#30000000
1#
b11010 %
#30500000
0#
#31000000
1#
b11011 %
#31500000
0#
#32000000
1#
b11100 %
#32500000
0#
#33000000
1#
b11101 %
#33500000
0#
#34000000
1#
b11110 %
#34500000
0#
#35000000
1#
b11111 %
#35500000
0#
#36000000
1#
b100000 %
#36500000
0#
#37000000
1#
b100001 %
#37500000
0#
#38000000
1#
b100010 %
#38500000
0#
#39000000
1#
b100011 %
#39500000
0#
#40000000
1#
b100100 %
#40500000
0#
#41000000
1#
b100101 %
#41500000
0#
#42000000
1#
b100110 %
#42500000
0#
#43000000
1#
b100111 %
#43500000
0#
#44000000
1#
b101000 %
#44500000
0#
#45000000
1#
b101001 %
#45500000
0#
#46000000
1#
b101010 %
#46500000
0#
#47000000
1#
b101011 %
#47500000
0#
#48000000
1#
b101100 %
#48500000
0#
#49000000
1#
b101101 %
#49500000
0#
#50000000
0"
1#
b101110 %
