sincos/sincos_simulation/tb_sincos.vhd
LIBRARY ieee  ; 
LIBRARY std  ; 
    USE ieee.NUMERIC_STD.all  ; 
    USE ieee.std_logic_1164.all  ; 
    USE ieee.std_logic_textio.all  ; 
    use ieee.math_real.all;
    USE std.textio.all  ; 

library math_library;
    use math_library.multiplier_pkg.all;
    use math_library.sincos_pkg.all;

entity tb_sincos is
end;

architecture sim of tb_sincos is
    signal rstn : std_logic;

    signal simulation_running : boolean;
    signal simulator_clock : std_logic;
    signal clocked_reset : std_logic;
    constant clock_per : time := 1 ns;
    constant clock_half_per : time := 0.5 ns;
    constant simtime_in_clocks : integer := 5000;
------------------------------------------------------------------------
    signal simulation_counter : natural := 0;

    signal angle_rad16 : unsigned(15 downto 0) := (others => '0');

    signal sincos_multiplier : multiplier_record := init_multiplier;
    signal sincos : sincos_record := init_sincos;
    signal sin : int18 := 0;
    signal cos : int18 := 32768;

begin

------------------------------------------------------------------------
    simtime : process
    begin
        simulation_running <= true;
        wait for simtime_in_clocks*clock_per;
        simulation_running <= false;
        wait;
    end process simtime;	

------------------------------------------------------------------------
    sim_clock_gen : process
    begin
        simulator_clock <= '0';
        rstn <= '0';
        simulator_clock <= '0';
        wait for clock_half_per;
        while simulation_running loop
            wait for clock_half_per;
                rstn <= '1';
                simulator_clock <= not simulator_clock;
            end loop;
            report "sincos finished";
        wait;
    end process;
------------------------------------------------------------------------

    clocked_reset_generator : process(simulator_clock, rstn)
    begin
        if rising_edge(simulator_clock) then
            simulation_counter <= simulation_counter + 1;

            create_multiplier(sincos_multiplier);
            create_sincos(sincos_multiplier, sincos);

            if simulation_counter = 10 or sincos_is_ready(sincos) then
                angle_rad16 <= angle_rad16 + 511;
                request_sincos(sincos, angle_rad16);
            end if; 
            if sincos_is_ready(sincos) then
                sin <= get_sine(sincos);
                cos <= get_cosine(sincos);
            end if;

        end if; -- rstn
    end process clocked_reset_generator;	
------------------------------------------------------------------------ 
end sim;

sincos/sincos_simulation/tb_sincos.vcd
$date
  Sun Sep 26 14:02:34 2021
$end
$version
  GHDL v0
$end
$timescale
  1 fs
$end
$scope module standard $end
$upscope $end
$scope module std_logic_1164 $end
$upscope $end
$scope module numeric_std $end
$upscope $end
$scope module textio $end
$upscope $end
$scope module std_logic_textio $end
$upscope $end
$scope module math_real $end
$upscope $end
$scope module multiplier_pkg $end
$upscope $end
$scope module sincos_pkg $end
$upscope $end
$scope module tb_sincos $end
$var reg 1 ! rstn $end
$var reg 1 " simulation_running $end
$var reg 1 # simulator_clock $end
$var reg 1 $ clocked_reset $end
$var integer 32 % simulation_counter $end
$var reg 16 & angle_rad16[15:0] $end
$comment sincos_multiplier is not handled $end
$comment sincos is not handled $end
$var integer 32 ' sin $end
$var integer 32 ( cos $end
$upscope $end
$enddefinitions $end
#0
0!
1"
0#
U$
b0 %
b0000000000000000 &
b0 '
b1000000000000000 (
#500000
#1000000
1!
1#
b1 %
#1500000
0#
#2000000
1#
b10 %
#2500000
0#
#3000000
1#
b11 %
#3500000
0#
#4000000
1#
b100 %
#4500000
0#
#5000000
1#
b101 %
#5500000
0#
#6000000
1#
b110 %
#6500000
0#
#7000000
1#
b111 %
#7500000
0#
#8000000
1#
b1000 %
#8500000
0#
#9000000
1#
b1001 %
#9500000
0#
#10000000
1#
b1010 %
#10500000
0#
#11000000
1#
b1011 %
b0000000111111111 &
#11500000
0#
#12000000
1#
b1100 %
#12500000
0#
#13000000
1#
b1101 %
#13500000
0#
#14000000
1#
b1110 %
#14500000
0#
#15000000
1#
b1111 %
#15500000
0#
#16000000
1#
b10000 %
#16500000
0#
#17000000
1#
b10001 %
#17500000
0#
#18000000
1#
b10010 %
#18500000
0#
#19000000
1#
b10011 %
#19500000
0#
#20000000
1#
b10100 %
#20500000
0#
#21000000
1#
b10101 %
#21500000
0#
#22000000
1#
b10110 %
#22500000
0#
#23000000
1#
b10111 %
#23500000
0#
#24000000
1#
b11000 %
#24500000
0#
#25000000
1#
b11001 %
#25500000
0#
#26000000
1#
b11010 %
#26500000
0#
#27000000
1#
b11011 %
#27500000
0#
#28000000
1#
b11100 %
#28500000
0#
#29000000
1#
b11101 %
#29500000
0#
#30000000
1#
b11110 %
b0000001111111110 &
#30500000
0#
#31000000
1#
b11111 %
#31500000
0#
#32000000
1#
b100000 %
#32500000
0#
#33000000
1#
b100001 %
#33500000
0#
#34000000
1#
b100010 %
#34500000
0#
#35000000
1#
b100011 %
#35500000
0#
#36000000
1#
b100100 %
#36500000
0#
#37000000
1#
b100101 %
#37500000
0#
#38000000
1#
b100110 %
#38500000
0#
#39000000
1#
b100111 %
#39500000
0#
#40000000
1#
b101000 %
#40500000
0#
#41000000
1#
b101001 %
#41500000
0#
#42000000
1#
b101010 %
#42500000
0#
#43000000
1#
b101011 %
#43500000
0#
#44000000
1#
b101100 %
#44500000
0#
#45000000
1#
b101101 %
#45500000
0#
#46000000
1#
b101110 %
#46500000
0#
#47000000
1#
b101111 %
#47500000
0#
#48000000
1#
b110000 %
#48500000
0#
#49000000
1#
b110001 %
b0000010111111101 &
b11001000101 '
b111111111011001 (
#49500000
0#
#50000000
1#
b110010 %
#50500000
0#
#51000000
1#
b110011 %
#51500000
0#
#52000000
1#
b110100 %
#52500000
0#
#53000000
1#
b110101 %
#53500000
0#
#54000000
1#
b110110 %
#54500000
0#
#55000000
1#
b110111 %
#55500000
0#
#56000000
1#
b111000 %
#56500000
0#
#57000000
1#
b111001 %
#57500000
0#
#58000000
1#
b111010 %
#58500000
0#
#59000000
1#
b111011 %
#59500000
0#
#60000000
1#
b111100 %
#60500000
0#
#61000000
1#
b111101 %
#61500000
0#
#62000000
1#
b111110 %
#62500000
0#
#63000000
1#
b111111 %
#63500000
0#
#64000000
1#
b1000000 %
#64500000
0#
#65000000
1#
b1000001 %
#65500000
0#
#66000000
1#
b1000010 %
#66500000
0#
#67000000
1#
b1000011 %
#67500000
0#
#68000000
1#
b1000100 %
b0000011111111100 &
b110010000101 '
b111111101100010 (
#68500000
0#
#69000000
1#
b1000101 %
#69500000
0#
#70000000
1#
b1000110 %
#70500000
0#
#71000000
1#
b1000111 %
#71500000
0#
#72000000
1#
b1001000 %
#72500000
0#
#73000000
1#
b1001001 %
#73500000
0#
#74000000
1#
b1001010 %
#74500000
0#
#75000000
1#
b1001011 %
#75500000
0#
#76000000
1#
b1001100 %
#76500000
0#
#77000000
1#
b1001101 %
#77500000
0#
#78000000
1#
b1001110 %
#78500000
0#
#79000000
1#
b1001111 %
#79500000
0#
#80000000
1#
b1010000 %
#80500000
0#
#81000000
1#
b1010001 %
#81500000
0#
#82000000
1#
b1010010 %
#82500000
0#
#83000000
1#
b1010011 %
#83500000
0#
#84000000
1#
b1010100 %
#84500000
0#
#85000000
1#
b1010101 %
#85500000
0#
#86000000
1#
b1010110 %
#86500000
0#
#87000000
1#
b1010111 %
b0000100111111011 &
b1001010111111 '
b111111010011110 (
#87500000
0#
#88000000
1#
b1011000 %
#88500000
0#
#89000000
1#
b1011001 %
#89500000
0#
#90000000
1#
b1011010 %
#90500000
0#
#91000000
1#
b1011011 %
#91500000
0#
#92000000
1#
b1011100 %
#92500000
0#
#93000000
1#
b1011101 %
#93500000
0#
#94000000
1#
b1011110 %
#94500000
0#
#95000000
1#
b1011111 %
#95500000
0#
#96000000
1#
b1100000 %
#96500000
0#
#97000000
1#
b1100001 %
#97500000
0#
#98000000
1#
b1100010 %
#98500000
0#
#99000000
1#
b1100011 %
#99500000
0#
#100000000
1#
b1100100 %
#100500000
0#
#101000000
1#
b1100101 %
#101500000
0#
#102000000
1#
b1100110 %
#102500000
0#
#103000000
1#
b1100111 %
#103500000
0#
#104000000
1#
b1101000 %
#104500000
0#
#105000000
1#
b1101001 %
#105500000
0#
#106000000
1#
b1101010 %
b0000101111111010 &
b1100011101101 '
b111110110001011 (
#106500000
0#
#107000000
1#
b1101011 %
#107500000
0#
#108000000
1#
b1101100 %
#108500000
0#
#109000000
1#
b1101101 %
#109500000
0#
#110000000
1#
b1101110 %
#110500000
0#
#111000000
1#
b1101111 %
#111500000
0#
#112000000
1#
b1110000 %
#112500000
0#
#113000000
1#
b1110001 %
#113500000
0#
#114000000
1#
b1110010 %
#114500000
0#
#115000000
1#
b1110011 %
#115500000
0#
#116000000
1#
b1110100 %
#116500000
0#
#117000000
1#
b1110101 %
#117500000
0#
#118000000
1#
b1110110 %
#118500000
0#
#119000000
1#
b1110111 %
#119500000
0#
#120000000
1#
b1111000 %
#120500000
0#
#121000000
1#
b1111001 %
#121500000
0#
#122000000
1#
b1111010 %
#122500000
0#
#123000000
1#
b1111011 %
#123500000
0#
#124000000
1#
b1111100 %
#124500000
0#
#125000000
1#
b1111101 %
b0000110111111001 &
b1111100001011 '
b111110000101111 (
#125500000
0#
#126000000
1#
b1111110 %
#126500000
0#
#127000000
1#
b1111111 %
#127500000
0#
#128000000
1#
b10000000 %
#128500000
0#
#129000000
1#
b10000001 %
#129500000
0#
#130000000
1#
b10000010 %
#130500000
0#
#131000000
1#
b10000011 %
#131500000
0#
#132000000
1#
b10000100 %
#132500000
0#
#133000000
1#
b10000101 %
#133500000
0#
#134000000
1#
b10000110 %
#134500000
0#
#135000000
1#
b10000111 %
#135500000
0#
#136000000
1#
b10001000 %
#136500000
0#
#137000000
1#
b10001001 %
#137500000
0#
#138000000
1#
b10001010 %
#138500000
0#
#139000000
1#
b10001011 %
#139500000
0#
#140000000
1#
b10001100 %
#140500000
0#
#141000000
1#
b10001101 %
#141500000
0#
#142000000
1#
b10001110 %
#142500000
0#
#143000000
1#
b10001111 %
#143500000
0#
#144000000
1#
b10010000 %
b0000111111111000 &
b10010100010110 '
b111101010000010 (
#144500000
0#
#145000000
1#
b10010001 %
#145500000
0#
#146000000
1#
b10010010 %
#146500000
0#
#147000000
1#
b10010011 %
#147500000
0#
#148000000
1#
b10010100 %
#148500000
0#
#149000000
1#
b10010101 %
#149500000
0#
#150000000
1#
b10010110 %
#150500000
0#
#151000000
1#
b10010111 %
#151500000
0#
#152000000
1#
b10011000 %
#152500000
0#
#153000000
1#
b10011001 %
#153500000
0#
#154000000
1#
b10011010 %
#154500000
0#
#155000000
1#
b10011011 %
#155500000
0#
#156000000
1#
b10011100 %
#156500000
0#
#157000000
1#
b10011101 %
#157500000
0#
#158000000
1#
b10011110 %
#158500000
0#
#159000000
1#
b10011111 %
#159500000
0#
#160000000
1#
b10100000 %
#160500000
0#
#161000000
1#
b10100001 %
#161500000
0#
#162000000
1#
b10100010 %
#162500000
0#
#163000000
1#
b10100011 %
b0001000111110111 &
b10101100001011 '
b111100010001111 (
#163500000
0#
#164000000
1#
b10100100 %
#164500000
0#
#165000000
1#
b10100101 %
#165500000
0#
#166000000
1#
b10100110 %
#166500000
0#
#167000000
1#
b10100111 %
#167500000
0#
#168000000
1#
b10101000 %
#168500000
0#
#169000000
1#
b10101001 %
#169500000
0#
#170000000
1#
b10101010 %
#170500000
0#
#171000000
1#
b10101011 %
#171500000
0#
#172000000
1#
b10101100 %
#172500000
0#
#173000000
1#
b10101101 %
#173500000
0#
#174000000
1#
b10101110 %
#174500000
0#
#175000000
1#
b10101111 %
#175500000
0#
#176000000
1#
b10110000 %
#176500000
0#
#177000000
1#
b10110001 %
#177500000
0#
#178000000
1#
b10110010 %
#178500000
0#
#179000000
1#
b10110011 %
#179500000
0#
#180000000
1#
b10110100 %
#180500000
0#
#181000000
1#
b10110101 %
#181500000
0#
#182000000
1#
b10110110 %
b0001001111110110 &
b11000011100101 '
b111011001001100 (
#182500000
0#
#183000000
1#
b10110111 %
#183500000
0#
#184000000
1#
b10111000 %
#184500000
0#
#185000000
1#
b10111001 %
#185500000
0#
#186000000
1#
b10111010 %
#186500000
0#
#187000000
1#
b10111011 %
#187500000
0#
#188000000
1#
b10111100 %
#188500000
0#
#189000000
1#
b10111101 %
#189500000
0#
#190000000
1#
b10111110 %
#190500000
0#
#191000000
1#
b10111111 %
#191500000
0#
#192000000
1#
b11000000 %
#192500000
0#
#193000000
1#
b11000001 %
#193500000
0#
#194000000
1#
b11000010 %
#194500000
0#
#195000000
1#
b11000011 %
#195500000
0#
#196000000
1#
b11000100 %
#196500000
0#
#197000000
1#
b11000101 %
#197500000
0#
#198000000
1#
b11000110 %
#198500000
0#
#199000000
1#
b11000111 %
#199500000
0#
#200000000
1#
b11001000 %
#200500000
0#
#201000000
1#
b11001001 %
b0001010111110101 &
b11011010100001 '
b111001111000101 (
#201500000
0#
#202000000
1#
b11001010 %
#202500000
0#
#203000000
1#
b11001011 %
#203500000
0#
#204000000
1#
b11001100 %
#204500000
0#
#205000000
1#
b11001101 %
#205500000
0#
#206000000
1#
b11001110 %
#206500000
0#
#207000000
1#
b11001111 %
#207500000
0#
#208000000
1#
b11010000 %
#208500000
0#
#209000000
1#
b11010001 %
#209500000
0#
#210000000
1#
b11010010 %
#210500000
0#
#211000000
1#
b11010011 %
#211500000
0#
#212000000
1#
b11010100 %
#212500000
0#
#213000000
1#
b11010101 %
#213500000
0#
#214000000
1#
b11010110 %
#214500000
0#
#215000000
1#
b11010111 %
#215500000
0#
#216000000
1#
b11011000 %
#216500000
0#
#217000000
1#
b11011001 %
#217500000
0#
#218000000
1#
b11011010 %
#218500000
0#
#219000000
1#
b11011011 %
#219500000
0#
#220000000
1#
b11011100 %
b0001011111110100 &
b11110000111011 '
b111000011110010 (
#220500000
0#
#221000000
1#
b11011101 %
#221500000
0#
#222000000
1#
b11011110 %
#222500000
0#
#223000000
1#
b11011111 %
#223500000
0#
#224000000
1#
b11100000 %
#224500000
0#
#225000000
1#
b11100001 %
#225500000
0#
#226000000
1#
b11100010 %
#226500000
0#
#227000000
1#
b11100011 %
#227500000
0#
#228000000
1#
b11100100 %
#228500000
0#
#229000000
1#
b11100101 %
#229500000
0#
#230000000
1#
b11100110 %
#230500000
0#
#231000000
1#
b11100111 %
#231500000
0#
#232000000
1#
b11101000 %
#232500000
0#
#233000000
1#
b11101001 %
#233500000
0#
#234000000
1#
b11101010 %
#234500000
0#
#235000000
1#
b11101011 %
#235500000
0#
#236000000
1#
b11101100 %
#236500000
0#
#237000000
1#
b11101101 %
#237500000
0#
#238000000
1#
b11101110 %
#238500000
0#
#239000000
1#
b11101111 %
b0001100111110011 &
b100000110110000 '
b110110111011101 (
#239500000
0#
#240000000
1#
b11110000 %
#240500000
0#
#241000000
1#
b11110001 %
#241500000
0#
#242000000
1#
b11110010 %
#242500000
0#
#243000000
1#
b11110011 %
#243500000
0#
#244000000
1#
b11110100 %
#244500000
0#
#245000000
1#
b11110101 %
#245500000
0#
#246000000
1#
b11110110 %
#246500000
0#
#247000000
1#
b11110111 %
#247500000
0#
#248000000
1#
b11111000 %
#248500000
0#
#249000000
1#
b11111001 %
#249500000
0#
#250000000
1#
b11111010 %
#250500000
0#
#251000000
1#
b11111011 %
#251500000
0#
#252000000
1#
b11111100 %
#252500000
0#
#253000000
1#
b11111101 %
#253500000
0#
#254000000
1#
b11111110 %
#254500000
0#
#255000000
1#
b11111111 %
#255500000
0#
#256000000
1#
b100000000 %
#256500000
0#
#257000000
1#
b100000001 %
#257500000
0#
#258000000
1#
b100000010 %
b0001101111110010 &
b100011011111101 '
b110101010000000 (
#258500000
0#
#259000000
1#
b100000011 %
#259500000
0#
#260000000
1#
b100000100 %
#260500000
0#
#261000000
1#
b100000101 %
#261500000
0#
#262000000
1#
b100000110 %
#262500000
0#
#263000000
1#
b100000111 %
#263500000
0#
#264000000
1#
b100001000 %
#264500000
0#
#265000000
1#
b100001001 %
#265500000
0#
#266000000
1#
b100001010 %
#266500000
0#
#267000000
1#
b100001011 %
#267500000
0#
#268000000
1#
b100001100 %
#268500000
0#
#269000000
1#
b100001101 %
#269500000
0#
#270000000
1#
b100001110 %
#270500000
0#
#271000000
1#
b100001111 %
#271500000
0#
#272000000
1#
b100010000 %
#272500000
0#
#273000000
1#
b100010001 %
#273500000
0#
#274000000
1#
b100010010 %
#274500000
0#
#275000000
1#
b100010011 %
#275500000
0#
#276000000
1#
b100010100 %
#276500000
0#
#277000000
1#
b100010101 %
b0001110111110001 &
b100110000011110 '
b110011011100111 (
#277500000
0#
#278000000
1#
b100010110 %
#278500000
0#
#279000000
1#
b100010111 %
#279500000
0#
#280000000
1#
b100011000 %
#280500000
0#
#281000000
1#
b100011001 %
#281500000
0#
#282000000
1#
b100011010 %
#282500000
0#
#283000000
1#
b100011011 %
#283500000
0#
#284000000
1#
b100011100 %
#284500000
0#
#285000000
1#
b100011101 %
#285500000
0#
#286000000
1#
b100011110 %
#286500000
0#
#287000000
1#
b100011111 %
#287500000
0#
#288000000
1#
b100100000 %
#288500000
0#
#289000000
1#
b100100001 %
#289500000
0#
#290000000
1#
b100100010 %
#290500000
0#
#291000000
1#
b100100011 %
#291500000
0#
#292000000
1#
b100100100 %
#292500000
0#
#293000000
1#
b100100101 %
#293500000
0#
#294000000
1#
b100100110 %
#294500000
0#
#295000000
1#
b100100111 %
#295500000
0#
#296000000
1#
b100101000 %
b0001111111110000 &
b101000100010011 '
b110001100001101 (
#296500000
0#
#297000000
1#
b100101001 %
#297500000
0#
#298000000
1#
b100101010 %
#298500000
0#
#299000000
1#
b100101011 %
#299500000
0#
#300000000
1#
b100101100 %
#300500000
0#
#301000000
1#
b100101101 %
#301500000
0#
#302000000
1#
b100101110 %
#302500000
0#
#303000000
1#
b100101111 %
#303500000
0#
#304000000
1#
b100110000 %
#304500000
0#
#305000000
1#
b100110001 %
#305500000
0#
#306000000
1#
b100110010 %
#306500000
0#
#307000000
1#
b100110011 %
#307500000
0#
#308000000
1#
b100110100 %
#308500000
0#
#309000000
1#
b100110101 %
#309500000
0#
#310000000
1#
b100110110 %
#310500000
0#
#311000000
1#
b100110111 %
#311500000
0#
#312000000
1#
b100111000 %
#312500000
0#
#313000000
1#
b100111001 %
#313500000
0#
#314000000
1#
b100111010 %
#314500000
0#
#315000000
1#
b100111011 %
b0010000111101111 &
b101010111010011 '
b101111011110111 (
#315500000
0#
#316000000
1#
b100111100 %
#316500000
0#
#317000000
1#
b100111101 %
#317500000
0#
#318000000
1#
b100111110 %
#318500000
0#
#319000000
1#
b100111111 %
#319500000
0#
#320000000
1#
b101000000 %
#320500000
0#
#321000000
1#
b101000001 %
#321500000
0#
#322000000
1#
b101000010 %
#322500000
0#
#323000000
1#
b101000011 %
#323500000
0#
#324000000
1#
b101000100 %
#324500000
0#
#325000000
1#
b101000101 %
#325500000
0#
#326000000
1#
b101000110 %
#326500000
0#
#327000000
1#
b101000111 %
#327500000
0#
#328000000
1#
b101001000 %
#328500000
0#
#329000000
1#
b101001001 %
#329500000
0#
#330000000
1#
b101001010 %
#330500000
0#
#331000000
1#
b101001011 %
#331500000
0#
#332000000
1#
b101001100 %
#332500000
0#
#333000000
1#
b101001101 %
#333500000
0#
#334000000
1#
b101001110 %
b0010001111101110 &
b101101001011111 '
b101101010100111 (
#334500000
0#
#335000000
1#
b101001111 %
#335500000
0#
#336000000
1#
b101010000 %
#336500000
0#
#337000000
1#
b101010001 %
#337500000
0#
#338000000
1#
b101010010 %
#338500000
0#
#339000000
1#
b101010011 %
#339500000
0#
#340000000
1#
b101010100 %
#340500000
0#
#341000000
1#
b101010101 %
#341500000
0#
#342000000
1#
b101010110 %
#342500000
0#
#343000000
1#
b101010111 %
#343500000
0#
#344000000
1#
b101011000 %
#344500000
0#
#345000000
1#
b101011001 %
#345500000
0#
#346000000
1#
b101011010 %
#346500000
0#
#347000000
1#
b101011011 %
#347500000
0#
#348000000
1#
b101011100 %
#348500000
0#
#349000000
1#
b101011101 %
#349500000
0#
#350000000
1#
b101011110 %
#350500000
0#
#351000000
1#
b101011111 %
#351500000
0#
#352000000
1#
b101100000 %
#352500000
0#
#353000000
1#
b101100001 %
b0010010111101101 &
b101111010110100 '
b101011000011111 (
#353500000
0#
#354000000
1#
b101100010 %
#354500000
0#
#355000000
1#
b101100011 %
#355500000
0#
#356000000
1#
b101100100 %
#356500000
0#
#357000000
1#
b101100101 %
#357500000
0#
#358000000
1#
b101100110 %
#358500000
0#
#359000000
1#
b101100111 %
#359500000
0#
#360000000
1#
b101101000 %
#360500000
0#
#361000000
1#
b101101001 %
#361500000
0#
#362000000
1#
b101101010 %
#362500000
0#
#363000000
1#
b101101011 %
#363500000
0#
#364000000
1#
b101101100 %
#364500000
0#
#365000000
1#
b101101101 %
#365500000
0#
#366000000
1#
b101101110 %
#366500000
0#
#367000000
1#
b101101111 %
#367500000
0#
#368000000
1#
b101110000 %
#368500000
0#
#369000000
1#
b101110001 %
#369500000
0#
#370000000
1#
b101110010 %
#370500000
0#
#371000000
1#
b101110011 %
#371500000
0#
#372000000
1#
b101110100 %
b0010011111101100 &
b110001011001110 '
b101000101100000 (
#372500000
0#
#373000000
1#
b101110101 %
#373500000
0#
#374000000
1#
b101110110 %
#374500000
0#
#375000000
1#
b101110111 %
#375500000
0#
#376000000
1#
b101111000 %
#376500000
0#
#377000000
1#
b101111001 %
#377500000
0#
#378000000
1#
b101111010 %
#378500000
0#
#379000000
1#
b101111011 %
#379500000
0#
#380000000
1#
b101111100 %
#380500000
0#
#381000000
1#
b101111101 %
#381500000
0#
#382000000
1#
b101111110 %
#382500000
0#
#383000000
1#
b101111111 %
#383500000
0#
#384000000
1#
b110000000 %
#384500000
0#
#385000000
1#
b110000001 %
#385500000
0#
#386000000
1#
b110000010 %
#386500000
0#
#387000000
1#
b110000011 %
#387500000
0#
#388000000
1#
b110000100 %
#388500000
0#
#389000000
1#
b110000101 %
#389500000
0#
#390000000
1#
b110000110 %
#390500000
0#
#391000000
1#
b110000111 %
b0010100111101011 &
b110011010101011 '
b100110001110000 (
#391500000
0#
#392000000
1#
b110001000 %
#392500000
0#
#393000000
1#
b110001001 %
#393500000
0#
#394000000
1#
b110001010 %
#394500000
0#
#395000000
1#
b110001011 %
#395500000
0#
#396000000
1#
b110001100 %
#396500000
0#
#397000000
1#
b110001101 %
#397500000
0#
#398000000
1#
b110001110 %
#398500000
0#
#399000000
1#
b110001111 %
#399500000
0#
#400000000
1#
b110010000 %
#400500000
0#
#401000000
1#
b110010001 %
#401500000
0#
#402000000
1#
b110010010 %
#402500000
0#
#403000000
1#
b110010011 %
#403500000
0#
#404000000
1#
b110010100 %
#404500000
0#
#405000000
1#
b110010101 %
#405500000
0#
#406000000
1#
b110010110 %
#406500000
0#
#407000000
1#
b110010111 %
#407500000
0#
#408000000
1#
b110011000 %
#408500000
0#
#409000000
1#
b110011001 %
#409500000
0#
#410000000
1#
b110011010 %
b0010101111101010 &
b110101001001001 '
b100011101010010 (
#410500000
0#
#411000000
1#
b110011011 %
#411500000
0#
#412000000
1#
b110011100 %
#412500000
0#
#413000000
1#
b110011101 %
#413500000
0#
#414000000
1#
b110011110 %
#414500000
0#
#415000000
1#
b110011111 %
#415500000
0#
#416000000
1#
b110100000 %
#416500000
0#
#417000000
1#
b110100001 %
#417500000
0#
#418000000
1#
b110100010 %
#418500000
0#
#419000000
1#
b110100011 %
#419500000
0#
#420000000
1#
b110100100 %
#420500000
0#
#421000000
1#
b110100101 %
#421500000
0#
#422000000
1#
b110100110 %
#422500000
0#
#423000000
1#
b110100111 %
#423500000
0#
#424000000
1#
b110101000 %
#424500000
0#
#425000000
1#
b110101001 %
#425500000
0#
#426000000
1#
b110101010 %
#426500000
0#
#427000000
1#
b110101011 %
#427500000
0#
#428000000
1#
b110101100 %
#428500000
0#
#429000000
1#
b110101101 %
b0010110111101001 &
b110110110101001 '
b100001000000111 (
#429500000
0#
#430000000
1#
b110101110 %
#430500000
0#
#431000000
1#
b110101111 %
#431500000
0#
#432000000
1#
b110110000 %
#432500000
0#
#433000000
1#
b110110001 %
#433500000
0#
#434000000
1#
b110110010 %
#434500000
0#
#435000000
1#
b110110011 %
#435500000
0#
#436000000
1#
b110110100 %
#436500000
0#
#437000000
1#
b110110101 %
#437500000
0#
#438000000
1#
b110110110 %
#438500000
0#
#439000000
1#
b110110111 %
#439500000
0#
#440000000
1#
b110111000 %
#440500000
0#
#441000000
1#
b110111001 %
#441500000
0#
#442000000
1#
b110111010 %
#442500000
0#
#443000000
1#
b110111011 %
#443500000
0#
#444000000
1#
b110111100 %
#444500000
0#
#445000000
1#
b110111101 %
#445500000
0#
#446000000
1#
b110111110 %
#446500000
0#
#447000000
1#
b110111111 %
#447500000
0#
#448000000
1#
b111000000 %
b0010111111101000 &
b111000011000010 '
b11110010010100 (
#448500000
0#
#449000000
1#
b111000001 %
#449500000
0#
#450000000
1#
b111000010 %
#450500000
0#
#451000000
1#
b111000011 %
#451500000
0#
#452000000
1#
b111000100 %
#452500000
0#
#453000000
1#
b111000101 %
#453500000
0#
#454000000
1#
b111000110 %
#454500000
0#
#455000000
1#
b111000111 %
#455500000
0#
#456000000
1#
b111001000 %
#456500000
0#
#457000000
1#
b111001001 %
#457500000
0#
#458000000
1#
b111001010 %
#458500000
0#
#459000000
1#
b111001011 %
#459500000
0#
#460000000
1#
b111001100 %
#460500000
0#
#461000000
1#
b111001101 %
#461500000
0#
#462000000
1#
b111001110 %
#462500000
0#
#463000000
1#
b111001111 %
#463500000
0#
#464000000
1#
b111010000 %
#464500000
0#
#465000000
1#
b111010001 %
#465500000
0#
#466000000
1#
b111010010 %
#466500000
0#
#467000000
1#
b111010011 %
b0011000111100111 &
b111001110011010 '
b11011011111101 (
#467500000
0#
#468000000
1#
b111010100 %
#468500000
0#
#469000000
1#
b111010101 %
#469500000
0#
#470000000
1#
b111010110 %
#470500000
0#
#471000000
1#
b111010111 %
#471500000
0#
#472000000
1#
b111011000 %
#472500000
0#
#473000000
1#
b111011001 %
#473500000
0#
#474000000
1#
b111011010 %
#474500000
0#
#475000000
1#
b111011011 %
#475500000
0#
#476000000
1#
b111011100 %
#476500000
0#
#477000000
1#
b111011101 %
#477500000
0#
#478000000
1#
b111011110 %
#478500000
0#
#479000000
1#
b111011111 %
#479500000
0#
#480000000
1#
b111100000 %
#480500000
0#
#481000000
1#
b111100001 %
#481500000
0#
#482000000
1#
b111100010 %
#482500000
0#
#483000000
1#
b111100011 %
#483500000
0#
#484000000
1#
b111100100 %
#484500000
0#
#485000000
1#
b111100101 %
#485500000
0#
#486000000
1#
b111100110 %
b0011001111100110 &
b111011000100101 '
b11000101000010 (
#486500000
0#
#487000000
1#
b111100111 %
#487500000
0#
#488000000
1#
b111101000 %
#488500000
0#
#489000000
1#
b111101001 %
#489500000
0#
#490000000
1#
b111101010 %
#490500000
0#
#491000000
1#
b111101011 %
#491500000
0#
#492000000
1#
b111101100 %
#492500000
0#
#493000000
1#
b111101101 %
#493500000
0#
#494000000
1#
b111101110 %
#494500000
0#
#495000000
1#
b111101111 %
#495500000
0#
#496000000
1#
b111110000 %
#496500000
0#
#497000000
1#
b111110001 %
#497500000
0#
#498000000
1#
b111110010 %
#498500000
0#
#499000000
1#
b111110011 %
#499500000
0#
#500000000
1#
b111110100 %
#500500000
0#
#501000000
1#
b111110101 %
#501500000
0#
#502000000
1#
b111110110 %
#502500000
0#
#503000000
1#
b111110111 %
#503500000
0#
#504000000
1#
b111111000 %
#504500000
0#
#505000000
1#
b111111001 %
b0011010111100101 &
b111100001101101 '
b10101101101010 (
#505500000
0#
#506000000
1#
b111111010 %
#506500000
0#
#507000000
1#
b111111011 %
#507500000
0#
#508000000
1#
b111111100 %
#508500000
0#
#509000000
1#
b111111101 %
#509500000
0#
#510000000
1#
b111111110 %
#510500000
0#
#511000000
1#
b111111111 %
#511500000
0#
#512000000
1#
b1000000000 %
#512500000
0#
#513000000
1#
b1000000001 %
#513500000
0#
#514000000
1#
b1000000010 %
#514500000
0#
#515000000
1#
b1000000011 %
#515500000
0#
#516000000
1#
b1000000100 %
#516500000
0#
#517000000
1#
b1000000101 %
#517500000
0#
#518000000
1#
b1000000110 %
#518500000
0#
#519000000
1#
b1000000111 %
#519500000
0#
#520000000
1#
b1000001000 %
#520500000
0#
#521000000
1#
b1000001001 %
#521500000
0#
#522000000
1#
b1000001010 %
#522500000
0#
#523000000
1#
b1000001011 %
#523500000
0#
#524000000
1#
b1000001100 %
b0011011111100100 &
b111101001100101 '
b10010101110111 (
#524500000
0#
#525000000
1#
b1000001101 %
#525500000
0#
#526000000
1#
b1000001110 %
#526500000
0#
#527000000
1#
b1000001111 %
#527500000
0#
#528000000
1#
b1000010000 %
#528500000
0#
#529000000
1#
b1000010001 %
#529500000
0#
#530000000
1#
b1000010010 %
#530500000
0#
#531000000
1#
b1000010011 %
#531500000
0#
#532000000
1#
b1000010100 %
#532500000
0#
#533000000
1#
b1000010101 %
#533500000
0#
#534000000
1#
b1000010110 %
#534500000
0#
#535000000
1#
b1000010111 %
#535500000
0#
#536000000
1#
b1000011000 %
#536500000
0#
#537000000
1#
b1000011001 %
#537500000
0#
#538000000
1#
b1000011010 %
#538500000
0#
#539000000
1#
b1000011011 %
#539500000
0#
#540000000
1#
b1000011100 %
#540500000
0#
#541000000
1#
b1000011101 %
#541500000
0#
#542000000
1#
b1000011110 %
#542500000
0#
#543000000
1#
b1000011111 %
b0011100111100011 &
b111110000010111 '
b1111101101101 (
#543500000
0#
#544000000
1#
b1000100000 %
#544500000
0#
#545000000
1#
b1000100001 %
#545500000
0#
#546000000
1#
b1000100010 %
#546500000
0#
#547000000
1#
b1000100011 %
#547500000
0#
#548000000
1#
b1000100100 %
#548500000
0#
#549000000
1#
b1000100101 %
#549500000
0#
#550000000
1#
b1000100110 %
#550500000
0#
#551000000
1#
b1000100111 %
#551500000
0#
#552000000
1#
b1000101000 %
#552500000
0#
#553000000
1#
b1000101001 %
#553500000
0#
#554000000
1#
b1000101010 %
#554500000
0#
#555000000
1#
b1000101011 %
#555500000
0#
#556000000
1#
b1000101100 %
