division/division_simulation/tb_nr_iterator.vhd
LIBRARY ieee  ; 
LIBRARY std  ; 
    USE ieee.NUMERIC_STD.all  ; 
    USE ieee.std_logic_1164.all  ; 
    USE ieee.std_logic_textio.all  ; 
    use ieee.math_real.all;
    USE std.textio.all  ; 

library math_library;
    use math_library.multiplier_pkg.all;
    use math_library.division_pkg.all;
    use math_library.division_internal_pkg.all;

entity tb_nr_iterator is
end;

architecture sim of tb_nr_iterator is
    signal rstn : std_logic;

    signal simulation_running : boolean;
    signal simulator_clock : std_logic;
    signal clocked_reset : std_logic;
    constant clock_per : time := 1 ns;
    constant clock_half_per : time := 0.5 ns;
    constant simtime_in_clocks : integer := 200;

    signal division_process_counter           : natural := 3;
    signal x                                  : int18 := 0;
    signal number_to_be_reciprocated          : int18 := 0;
    signal number_of_newton_raphson_iteration : int18 := 0;
    signal dividend                           : int18 := 0;
    signal divisor                            : int18 := 0;

    signal hw_multiplier : multiplier_record := multiplier_init_values;

    signal simulation_counter : natural := 0;

    signal check_division_to_be_ready : boolean := false;
    signal test_division : natural := 250;

    signal division_multiplier : multiplier_record := multiplier_init_values;
    signal divider             : division_record := init_division;

begin

------------------------------------------------------------------------
    simtime : process
    begin
        simulation_running <= true;
        wait for simtime_in_clocks*clock_per;
        simulation_running <= false;
        wait;
    end process simtime;	

------------------------------------------------------------------------
    sim_clock_gen : process
    begin
        simulator_clock <= '0';
        rstn <= '0';
        simulator_clock <= '0';
        wait for clock_half_per;
        while simulation_running loop
            wait for clock_half_per;
                rstn <= '1';
                simulator_clock <= not simulator_clock;
            end loop;
        wait;
    end process;
------------------------------------------------------------------------

    clocked_reset_generator : process(simulator_clock, rstn)
    --------------------------------------------------
        variable xa : int18;
    --------------------------------------------------
    begin 
        if rising_edge(simulator_clock) then
        --------------------------------------------------
            create_multiplier(division_multiplier);
            create_division(division_multiplier, divider);

            create_multiplier(hw_multiplier);
        --------------------------------------------------
            CASE division_process_counter is
                WHEN 0 =>
                    check_division_to_be_ready <= false;
                    multiply(hw_multiplier, x, number_to_be_reciprocated);
                    division_process_counter <= division_process_counter + 1;
                WHEN 1 =>
                    check_division_to_be_ready <= false;
                    increment_counter_when_ready(hw_multiplier,division_process_counter);
                    if multiplier_is_ready(hw_multiplier) then
                        multiply(hw_multiplier, x, invert_bits(get_multiplier_result(hw_multiplier, 16)));
                    end if;
                WHEN 2 =>
                    check_division_to_be_ready <= false;
                    if multiplier_is_ready(hw_multiplier) then
                        x <= get_multiplier_result(hw_multiplier, 16);
                        if number_of_newton_raphson_iteration /= 0 then
                            number_of_newton_raphson_iteration <= number_of_newton_raphson_iteration - 1;
                            division_process_counter <= 0;
                        else
                            division_process_counter <= division_process_counter + 1;
                            multiply(hw_multiplier, dividend, get_multiplier_result(hw_multiplier, 16));
                            check_division_to_be_ready <= true;
                        end if;
                    end if;
                WHEN others => -- wait for start
                    if multiplier_is_ready(hw_multiplier) then
                        check_division_to_be_ready <= false;
                    end if;
            end CASE;

            simulation_counter <= simulation_counter + 1;
            if simulation_counter = 10 then
                x                                  <= get_initial_value_for_division(remove_leading_zeros(test_division));
                number_to_be_reciprocated          <= (remove_leading_zeros(test_division));
                dividend                           <= test_division/128;
                divisor                            <= test_division;
                division_process_counter           <= 0;
                number_of_newton_raphson_iteration <= 1;
                request_division(divider, test_division/128, test_division, 1);
                -- test_division <= test_division + 1;
            end if;


            -- if multiplier_is_ready(hw_multiplier) and check_division_to_be_ready then
            --     report "result from state machine " & integer'image(get_division_result(hw_multiplier,test_division,17));
            -- end if; 
            if division_is_ready(division_multiplier, divider) then 
                report "result from divider " & integer'image(get_division_result(division_multiplier,test_division,17))& " " & integer'image(test_division);
                test_division <= test_division + 1;
                request_division(divider, test_division/128, test_division, 1);
            end if;
    
        end if; -- rstn
    end process clocked_reset_generator;	
------------------------------------------------------------------------

end sim;

division/division_simulation/tb_nr_iterator.vcd
$date
  Sun Sep 26 14:02:32 2021
$end
$version
  GHDL v0
$end
$timescale
  1 fs
$end
$scope module standard $end
$upscope $end
$scope module std_logic_1164 $end
$upscope $end
$scope module numeric_std $end
$upscope $end
$scope module textio $end
$upscope $end
$scope module std_logic_textio $end
$upscope $end
$scope module math_real $end
$upscope $end
$scope module multiplier_pkg $end
$upscope $end
$scope module division_internal_pkg $end
$upscope $end
$scope module division_pkg $end
$upscope $end
$scope module tb_nr_iterator $end
$var reg 1 ! rstn $end
$var reg 1 " simulation_running $end
$var reg 1 # simulator_clock $end
$var reg 1 $ clocked_reset $end
$var integer 32 % division_process_counter $end
$var integer 32 & x $end
$var integer 32 ' number_to_be_reciprocated $end
$var integer 32 ( number_of_newton_raphson_iteration $end
$var integer 32 ) dividend $end
$var integer 32 * divisor $end
$comment hw_multiplier is not handled $end
$var integer 32 + simulation_counter $end
$var reg 1 , check_division_to_be_ready $end
$var integer 32 - test_division $end
$comment division_multiplier is not handled $end
$comment divider is not handled $end
$upscope $end
$enddefinitions $end
#0
0!
1"
0#
U$
b11 %
b0 &
b0 '
b0 (
b0 )
b0 *
b0 +
0,
b11111010 -
#500000
#1000000
1!
1#
b1 +
#1500000
0#
#2000000
1#
b10 +
#2500000
0#
#3000000
1#
b11 +
#3500000
0#
#4000000
1#
b100 +
#4500000
0#
#5000000
1#
b101 +
#5500000
0#
#6000000
1#
b110 +
#6500000
0#
#7000000
1#
b111 +
#7500000
0#
#8000000
1#
b1000 +
#8500000
0#
#9000000
1#
b1001 +
#9500000
0#
#10000000
1#
b1010 +
#10500000
0#
#11000000
1#
b0 %
b10000000000000000 &
b1111101000000000 '
b1 (
b1 )
b11111010 *
b1011 +
#11500000
0#
#12000000
1#
b1 %
b1100 +
#12500000
0#
#13000000
1#
b1101 +
#13500000
0#
#14000000
1#
b1110 +
#14500000
0#
#15000000
1#
b1111 +
#15500000
0#
#16000000
1#
b10 %
b10000 +
#16500000
0#
#17000000
1#
b10001 +
#17500000
0#
#18000000
1#
b10010 +
#18500000
0#
#19000000
1#
b10011 +
#19500000
0#
#20000000
1#
b0 %
b10000010111111111 &
b0 (
b10100 +
#20500000
0#
#21000000
1#
b1 %
b10101 +
#21500000
0#
#22000000
1#
b10110 +
#22500000
0#
#23000000
1#
b10111 +
#23500000
0#
#24000000
1#
b11000 +
b11111011 -
#24500000
0#
#25000000
1#
b10 %
b11001 +
#25500000
0#
#26000000
1#
b11010 +
#26500000
0#
#27000000
1#
b11011 +
#27500000
0#
#28000000
1#
b11100 +
#28500000
0#
#29000000
1#
b11 %
b10000011000100100 &
b11101 +
1,
#29500000
0#
#30000000
1#
b11110 +
#30500000
0#
#31000000
1#
b11111 +
#31500000
0#
#32000000
1#
b100000 +
#32500000
0#
#33000000
1#
b100001 +
0,
#33500000
0#
#34000000
1#
b100010 +
#34500000
0#
#35000000
1#
b100011 +
#35500000
0#
#36000000
1#
b100100 +
#36500000
0#
#37000000
1#
b100101 +
b11111100 -
#37500000
0#
#38000000
1#
b100110 +
#38500000
0#
#39000000
1#
b100111 +
#39500000
0#
#40000000
1#
b101000 +
#40500000
0#
#41000000
1#
b101001 +
#41500000
0#
#42000000
1#
b101010 +
#42500000
0#
#43000000
1#
b101011 +
#43500000
0#
#44000000
1#
b101100 +
#44500000
0#
#45000000
1#
b101101 +
#45500000
0#
#46000000
1#
b101110 +
#46500000
0#
#47000000
1#
b101111 +
#47500000
0#
#48000000
1#
b110000 +
#48500000
0#
#49000000
1#
b110001 +
#49500000
0#
#50000000
1#
b110010 +
b11111101 -
#50500000
0#
#51000000
1#
b110011 +
#51500000
0#
#52000000
1#
b110100 +
#52500000
0#
#53000000
1#
b110101 +
#53500000
0#
#54000000
1#
b110110 +
#54500000
0#
#55000000
1#
b110111 +
#55500000
0#
#56000000
1#
b111000 +
#56500000
0#
#57000000
1#
b111001 +
#57500000
0#
#58000000
1#
b111010 +
#58500000
0#
#59000000
1#
b111011 +
#59500000
0#
#60000000
1#
b111100 +
#60500000
0#
#61000000
1#
b111101 +
#61500000
0#
#62000000
1#
b111110 +
#62500000
0#
#63000000
1#
b111111 +
b11111110 -
#63500000
0#
#64000000
1#
b1000000 +
#64500000
0#
#65000000
1#
b1000001 +
#65500000
0#
#66000000
1#
b1000010 +
#66500000
0#
#67000000
1#
b1000011 +
#67500000
0#
#68000000
1#
b1000100 +
#68500000
0#
#69000000
1#
b1000101 +
#69500000
0#
#70000000
1#
b1000110 +
#70500000
0#
#71000000
1#
b1000111 +
#71500000
0#
#72000000
1#
b1001000 +
#72500000
0#
#73000000
1#
b1001001 +
#73500000
0#
#74000000
1#
b1001010 +
#74500000
0#
#75000000
1#
b1001011 +
#75500000
0#
#76000000
1#
b1001100 +
b11111111 -
#76500000
0#
#77000000
1#
b1001101 +
#77500000
0#
#78000000
1#
b1001110 +
#78500000
0#
#79000000
1#
b1001111 +
#79500000
0#
#80000000
1#
b1010000 +
#80500000
0#
#81000000
1#
b1010001 +
#81500000
0#
#82000000
1#
b1010010 +
#82500000
0#
#83000000
1#
b1010011 +
#83500000
0#
#84000000
1#
b1010100 +
#84500000
0#
#85000000
1#
b1010101 +
#85500000
0#
#86000000
1#
b1010110 +
#86500000
0#
#87000000
1#
b1010111 +
#87500000
0#
#88000000
1#
b1011000 +
#88500000
0#
#89000000
1#
b1011001 +
b100000000 -
#89500000
0#
#90000000
1#
b1011010 +
#90500000
0#
#91000000
1#
b1011011 +
#91500000
0#
#92000000
1#
b1011100 +
#92500000
0#
#93000000
1#
b1011101 +
#93500000
0#
#94000000
1#
b1011110 +
#94500000
0#
#95000000
1#
b1011111 +
#95500000
0#
#96000000
1#
b1100000 +
#96500000
0#
#97000000
1#
b1100001 +
#97500000
0#
#98000000
1#
b1100010 +
#98500000
0#
#99000000
1#
b1100011 +
#99500000
0#
#100000000
1#
b1100100 +
#100500000
0#
#101000000
1#
b1100101 +
#101500000
0#
#102000000
1#
b1100110 +
b100000001 -
#102500000
0#
#103000000
1#
b1100111 +
#103500000
0#
#104000000
1#
b1101000 +
#104500000
0#
#105000000
1#
b1101001 +
#105500000
0#
#106000000
1#
b1101010 +
#106500000
0#
#107000000
1#
b1101011 +
#107500000
0#
#108000000
1#
b1101100 +
#108500000
0#
#109000000
1#
b1101101 +
#109500000
0#
#110000000
1#
b1101110 +
#110500000
0#
#111000000
1#
b1101111 +
#111500000
0#
#112000000
1#
b1110000 +
#112500000
0#
#113000000
1#
b1110001 +
#113500000
0#
#114000000
1#
b1110010 +
#114500000
0#
#115000000
1#
b1110011 +
b100000010 -
#115500000
0#
#116000000
1#
b1110100 +
#116500000
0#
#117000000
1#
b1110101 +
#117500000
0#
#118000000
1#
b1110110 +
#118500000
0#
#119000000
1#
b1110111 +
#119500000
0#
#120000000
1#
b1111000 +
#120500000
0#
#121000000
1#
b1111001 +
#121500000
0#
#122000000
1#
b1111010 +
#122500000
0#
#123000000
1#
b1111011 +
#123500000
0#
#124000000
1#
b1111100 +
#124500000
0#
#125000000
1#
b1111101 +
#125500000
0#
#126000000
1#
b1111110 +
#126500000
0#
#127000000
1#
b1111111 +
#127500000
0#
#128000000
1#
b10000000 +
b100000011 -
#128500000
0#
#129000000
1#
b10000001 +
#129500000
0#
#130000000
1#
b10000010 +
#130500000
0#
#131000000
1#
b10000011 +
#131500000
0#
#132000000
1#
b10000100 +
#132500000
0#
#133000000
1#
b10000101 +
#133500000
0#
#134000000
1#
b10000110 +
#134500000
0#
#135000000
1#
b10000111 +
#135500000
0#
#136000000
1#
b10001000 +
#136500000
0#
#137000000
1#
b10001001 +
#137500000
0#
#138000000
1#
b10001010 +
#138500000
0#
#139000000
1#
b10001011 +
#139500000
0#
#140000000
1#
b10001100 +
#140500000
0#
#141000000
1#
b10001101 +
b100000100 -
#141500000
0#
#142000000
1#
b10001110 +
#142500000
0#
#143000000
1#
b10001111 +
#143500000
0#
#144000000
1#
b10010000 +
#144500000
0#
#145000000
1#
b10010001 +
#145500000
0#
#146000000
1#
b10010010 +
#146500000
0#
#147000000
1#
b10010011 +
#147500000
0#
#148000000
1#
b10010100 +
#148500000
0#
#149000000
1#
b10010101 +
#149500000
0#
#150000000
1#
b10010110 +
#150500000
0#
#151000000
1#
b10010111 +
#151500000
0#
#152000000
1#
b10011000 +
#152500000
0#
#153000000
1#
b10011001 +
#153500000
0#
#154000000
1#
b10011010 +
b100000101 -
#154500000
0#
#155000000
1#
b10011011 +
#155500000
0#
#156000000
1#
b10011100 +
#156500000
0#
#157000000
1#
b10011101 +
#157500000
0#
#158000000
1#
b10011110 +
#158500000
0#
#159000000
1#
b10011111 +
#159500000
0#
#160000000
1#
b10100000 +
#160500000
0#
#161000000
1#
b10100001 +
#161500000
0#
#162000000
1#
b10100010 +
#162500000
0#
#163000000
1#
b10100011 +
#163500000
0#
#164000000
1#
b10100100 +
#164500000
0#
#165000000
1#
b10100101 +
#165500000
0#
#166000000
1#
b10100110 +
#166500000
0#
#167000000
1#
b10100111 +
b100000110 -
#167500000
0#
#168000000
1#
b10101000 +
#168500000
0#
#169000000
1#
b10101001 +
#169500000
0#
#170000000
1#
b10101010 +
#170500000
0#
#171000000
1#
b10101011 +
#171500000
0#
#172000000
1#
b10101100 +
#172500000
0#
#173000000
1#
b10101101 +
#173500000
0#
#174000000
1#
b10101110 +
#174500000
0#
#175000000
1#
b10101111 +
#175500000
0#
#176000000
1#
b10110000 +
#176500000
0#
#177000000
1#
b10110001 +
#177500000
0#
#178000000
1#
b10110010 +
#178500000
0#
#179000000
1#
b10110011 +
#179500000
0#
#180000000
1#
b10110100 +
b100000111 -
#180500000
0#
#181000000
1#
b10110101 +
#181500000
0#
#182000000
1#
b10110110 +
#182500000
0#
#183000000
1#
b10110111 +
#183500000
0#
#184000000
1#
b10111000 +
#184500000
0#
#185000000
1#
b10111001 +
#185500000
0#
#186000000
1#
b10111010 +
#186500000
0#
#187000000
1#
b10111011 +
#187500000
0#
#188000000
1#
b10111100 +
#188500000
0#
#189000000
1#
b10111101 +
#189500000
0#
#190000000
1#
b10111110 +
#190500000
0#
#191000000
1#
b10111111 +
#191500000
0#
#192000000
1#
b11000000 +
#192500000
0#
#193000000
1#
b11000001 +
b100001000 -
#193500000
0#
#194000000
1#
b11000010 +
#194500000
0#
#195000000
1#
b11000011 +
#195500000
0#
#196000000
1#
b11000100 +
#196500000
0#
#197000000
1#
b11000101 +
#197500000
0#
#198000000
1#
b11000110 +
#198500000
0#
#199000000
1#
b11000111 +
#199500000
0#
#200000000
0"
1#
b11001000 +
